[{
		"fields": {
			"name": "Adur District Council",
			"domain_name": "adur-worthing.gov.uk",
			"organisation_region": 6,
			"organisation_type": 5
		},
		"model": "assessment.organisation",
		"pk": 1
	},
	{
		"fields": {
			"name": "Allerdale District Council",
			"domain_name": "allerdale.gov.uk",
			"organisation_region": 5,
			"organisation_type": 5
		},
		"model": "assessment.organisation",
		"pk": 2
	},
	{
		"fields": {
			"name": "Amber Valley Borough Council",
			"domain_name": "ambervalley.gov.uk",
			"organisation_region": 1,
			"organisation_type": 5
		},
		"model": "assessment.organisation",
		"pk": 3
	},
	{
		"fields": {
			"name": "Arun District Council",
			"domain_name": "arun.gov.uk",
			"organisation_region": 6,
			"organisation_type": 5
		},
		"model": "assessment.organisation",
		"pk": 4
	},
	{
		"fields": {
			"name": "Ashfield District Council",
			"domain_name": "ashfield-dc.gov.uk",
			"organisation_region": 1,
			"organisation_type": 5
		},
		"model": "assessment.organisation",
		"pk": 5
	},
	{
		"fields": {
			"name": "Ashford Borough Council",
			"domain_name": "ashford.gov.uk",
			"organisation_region": 6,
			"organisation_type": 5
		},
		"model": "assessment.organisation",
		"pk": 6
	},
	{
		"fields": {
			"name": "Aylesbury Vale District Council",
			"domain_name": "aylesburyvaledc.gov.uk",
			"organisation_region": 6,
			"organisation_type": 5
		},
		"model": "assessment.organisation",
		"pk": 7
	},
	{
		"fields": {
			"name": "Babergh District Council",
			"domain_name": "babergh.gov.uk",
			"organisation_region": 2,
			"organisation_type": 5
		},
		"model": "assessment.organisation",
		"pk": 8
	},
	{
		"fields": {
			"name": "Barking and Dagenham",
			"domain_name": "lbbd.gov.uk",
			"organisation_region": 3,
			"organisation_type": 2
		},
		"model": "assessment.organisation",
		"pk": 9
	},
	{
		"fields": {
			"name": "Barnet",
			"domain_name": "barnet.gov.uk",
			"organisation_region": 3,
			"organisation_type": 2
		},
		"model": "assessment.organisation",
		"pk": 10
	},
	{
		"fields": {
			"name": "Barnsley Borough Council",
			"domain_name": "barnsley.gov.uk",
			"organisation_region": 9,
			"organisation_type": 1
		},
		"model": "assessment.organisation",
		"pk": 11
	},
	{
		"fields": {
			"name": "Barrow-in-Furness Borough Council",
			"domain_name": "barrowbc.gov.uk",
			"organisation_region": 5,
			"organisation_type": 5
		},
		"model": "assessment.organisation",
		"pk": 12
	},
	{
		"fields": {
			"name": "Basildon Borough Council",
			"domain_name": "basildon.gov.uk",
			"organisation_region": 2,
			"organisation_type": 5
		},
		"model": "assessment.organisation",
		"pk": 13
	},
	{
		"fields": {
			"name": "Basingstoke & Deane Borough Council",
			"domain_name": "basingstoke.gov.uk",
			"organisation_region": 6,
			"organisation_type": 5
		},
		"model": "assessment.organisation",
		"pk": 14
	},
	{
		"fields": {
			"name": "Bassetlaw District Council",
			"domain_name": "bassetlaw.gov.uk",
			"organisation_region": 1,
			"organisation_type": 5
		},
		"model": "assessment.organisation",
		"pk": 15
	},
	{
		"fields": {
			"name": "Bath and North East Somerset Council",
			"domain_name": "bathnes.gov.uk",
			"organisation_region": 7,
			"organisation_type": 3
		},
		"model": "assessment.organisation",
		"pk": 16
	},
	{
		"fields": {
			"name": "Bedford Borough Council",
			"domain_name": "bedford.gov.uk",
			"organisation_region": 2,
			"organisation_type": 3
		},
		"model": "assessment.organisation",
		"pk": 17
	},
	{
		"fields": {
			"name": "Bexley",
			"domain_name": "bexley.gov.uk",
			"organisation_region": 3,
			"organisation_type": 2
		},
		"model": "assessment.organisation",
		"pk": 18
	},
	{
		"fields": {
			"name": "Birmingham City Council",
			"domain_name": "birmingham.gov.uk",
			"organisation_region": 8,
			"organisation_type": 1
		},
		"model": "assessment.organisation",
		"pk": 19
	},
	{
		"fields": {
			"name": "Blaby District Council",
			"domain_name": "blaby.gov.uk",
			"organisation_region": 1,
			"organisation_type": 5
		},
		"model": "assessment.organisation",
		"pk": 20
	},
	{
		"fields": {
			"name": "Blackburn with Darwen Borough Council",
			"domain_name": "blackburn.gov.uk",
			"organisation_region": 5,
			"organisation_type": 3
		},
		"model": "assessment.organisation",
		"pk": 21
	},
	{
		"fields": {
			"name": "Blackpool Council",
			"domain_name": "blackpool.gov.uk",
			"organisation_region": 5,
			"organisation_type": 3
		},
		"model": "assessment.organisation",
		"pk": 22
	},
	{
		"fields": {
			"name": "Bolsover District Council",
			"domain_name": "bolsover.gov.uk",
			"organisation_region": 1,
			"organisation_type": 5
		},
		"model": "assessment.organisation",
		"pk": 23
	},
	{
		"fields": {
			"name": "Bolton Borough Council",
			"domain_name": "bolton.gov.uk",
			"organisation_region": 5,
			"organisation_type": 1
		},
		"model": "assessment.organisation",
		"pk": 24
	},
	{
		"fields": {
			"name": "Boston Borough Council",
			"domain_name": "boston.gov.uk",
			"organisation_region": 1,
			"organisation_type": 5
		},
		"model": "assessment.organisation",
		"pk": 25
	},
	{
		"fields": {
			"name": "Bournemouth, Christchurch and Poole Council",
			"domain_name": "bournemouth.gov.uk",
			"organisation_region": 7,
			"organisation_type": 3
		},
		"model": "assessment.organisation",
		"pk": 26
	},
	{
		"fields": {
			"name": "Bracknell Forest Borough Council",
			"domain_name": "bracknell-forest.gov.uk",
			"organisation_region": 6,
			"organisation_type": 3
		},
		"model": "assessment.organisation",
		"pk": 27
	},
	{
		"fields": {
			"name": "Bradford City Council",
			"domain_name": "bradford.gov.uk",
			"organisation_region": 9,
			"organisation_type": 1
		},
		"model": "assessment.organisation",
		"pk": 28
	},
	{
		"fields": {
			"name": "Braintree District Council",
			"domain_name": "braintree.gov.uk",
			"organisation_region": 2,
			"organisation_type": 5
		},
		"model": "assessment.organisation",
		"pk": 29
	},
	{
		"fields": {
			"name": "Breckland District Council",
			"domain_name": "breckland.gov.uk",
			"organisation_region": 2,
			"organisation_type": 5
		},
		"model": "assessment.organisation",
		"pk": 30
	},
	{
		"fields": {
			"name": "Brent",
			"domain_name": "brent.gov.uk",
			"organisation_region": 3,
			"organisation_type": 2
		},
		"model": "assessment.organisation",
		"pk": 31
	},
	{
		"fields": {
			"name": "Brentwood Borough Council",
			"domain_name": "brentwood.gov.uk",
			"organisation_region": 2,
			"organisation_type": 5
		},
		"model": "assessment.organisation",
		"pk": 32
	},
	{
		"fields": {
			"name": "Brighton and Hove City Council",
			"domain_name": "brighton-hove.gov.uk",
			"organisation_region": 6,
			"organisation_type": 3
		},
		"model": "assessment.organisation",
		"pk": 33
	},
	{
		"fields": {
			"name": "Bristol City Council",
			"domain_name": "bristol.gov.uk",
			"organisation_region": 7,
			"organisation_type": 3
		},
		"model": "assessment.organisation",
		"pk": 34
	},
	{
		"fields": {
			"name": "Broadland District Council",
			"domain_name": "broadland.gov.uk",
			"organisation_region": 2,
			"organisation_type": 5
		},
		"model": "assessment.organisation",
		"pk": 35
	},
	{
		"fields": {
			"name": "Bromley",
			"domain_name": "bromley.gov.uk",
			"organisation_region": 3,
			"organisation_type": 2
		},
		"model": "assessment.organisation",
		"pk": 36
	},
	{
		"fields": {
			"name": "Bromsgrove District Council",
			"domain_name": "bromsgrove.gov.uk",
			"organisation_region": 8,
			"organisation_type": 5
		},
		"model": "assessment.organisation",
		"pk": 37
	},
	{
		"fields": {
			"name": "Broxbourne Borough Council",
			"domain_name": "broxbourne.gov.uk",
			"organisation_region": 2,
			"organisation_type": 5
		},
		"model": "assessment.organisation",
		"pk": 38
	},
	{
		"fields": {
			"name": "Broxtowe Borough Council",
			"domain_name": "broxtowe.gov.uk",
			"organisation_region": 1,
			"organisation_type": 5
		},
		"model": "assessment.organisation",
		"pk": 39
	},
	{
		"fields": {
			"name": "Buckinghamshire County Council",
			"domain_name": "buckscc.gov.uk",
			"organisation_region": 6,
			"organisation_type": 4
		},
		"model": "assessment.organisation",
		"pk": 40
	},
	{
		"fields": {
			"name": "Burnley Borough Council",
			"domain_name": "burnley.gov.uk",
			"organisation_region": 5,
			"organisation_type": 5
		},
		"model": "assessment.organisation",
		"pk": 41
	},
	{
		"fields": {
			"name": "Bury Borough Council",
			"domain_name": "bury.gov.uk",
			"organisation_region": 5,
			"organisation_type": 1
		},
		"model": "assessment.organisation",
		"pk": 42
	},
	{
		"fields": {
			"name": "Calderdale Borough Council",
			"domain_name": "calderdale.gov.uk",
			"organisation_region": 9,
			"organisation_type": 1
		},
		"model": "assessment.organisation",
		"pk": 43
	},
	{
		"fields": {
			"name": "Cambridge City Council",
			"domain_name": "cambridge.gov.uk",
			"organisation_region": 2,
			"organisation_type": 5
		},
		"model": "assessment.organisation",
		"pk": 44
	},
	{
		"fields": {
			"name": "Cambridgeshire County Council",
			"domain_name": "cambridgeshire.gov.uk",
			"organisation_region": 2,
			"organisation_type": 4
		},
		"model": "assessment.organisation",
		"pk": 45
	},
	{
		"fields": {
			"name": "Camden",
			"domain_name": "camden.gov.uk",
			"organisation_region": 3,
			"organisation_type": 2
		},
		"model": "assessment.organisation",
		"pk": 46
	},
	{
		"fields": {
			"name": "Cannock Chase District Council",
			"domain_name": "cannockchasedc.gov.uk",
			"organisation_region": 8,
			"organisation_type": 5
		},
		"model": "assessment.organisation",
		"pk": 47
	},
	{
		"fields": {
			"name": "Canterbury City Council",
			"domain_name": "canterbury.gov.uk",
			"organisation_region": 6,
			"organisation_type": 5
		},
		"model": "assessment.organisation",
		"pk": 48
	},
	{
		"fields": {
			"name": "Carlisle City Council",
			"domain_name": "carlisle.gov.uk",
			"organisation_region": 5,
			"organisation_type": 5
		},
		"model": "assessment.organisation",
		"pk": 49
	},
	{
		"fields": {
			"name": "Castle Point District Council",
			"domain_name": "castlepoint.gov.uk",
			"organisation_region": 2,
			"organisation_type": 5
		},
		"model": "assessment.organisation",
		"pk": 50
	},
	{
		"fields": {
			"name": "Central Bedfordshire Council",
			"domain_name": "centralbedfordshire.gov.uk",
			"organisation_region": 2,
			"organisation_type": 3
		},
		"model": "assessment.organisation",
		"pk": 51
	},
	{
		"fields": {
			"name": "Charnwood Borough Council",
			"domain_name": "charnwood.gov.uk",
			"organisation_region": 1,
			"organisation_type": 5
		},
		"model": "assessment.organisation",
		"pk": 52
	},
	{
		"fields": {
			"name": "Chelmsford City Council",
			"domain_name": "chelmsford.gov.uk",
			"organisation_region": 2,
			"organisation_type": 5
		},
		"model": "assessment.organisation",
		"pk": 53
	},
	{
		"fields": {
			"name": "Cheltenham Borough Council",
			"domain_name": "cheltenham.gov.uk",
			"organisation_region": 7,
			"organisation_type": 5
		},
		"model": "assessment.organisation",
		"pk": 54
	},
	{
		"fields": {
			"name": "Cherwell District Council",
			"domain_name": "cherwell-dc.gov.uk",
			"organisation_region": 6,
			"organisation_type": 5
		},
		"model": "assessment.organisation",
		"pk": 55
	},
	{
		"fields": {
			"name": "Cheshire East Council",
			"domain_name": "cheshireeast.gov.uk",
			"organisation_region": 5,
			"organisation_type": 3
		},
		"model": "assessment.organisation",
		"pk": 56
	},
	{
		"fields": {
			"name": "Cheshire West and Chester Council",
			"domain_name": "cheshirewestandchester.gov.uk",
			"organisation_region": 5,
			"organisation_type": 3
		},
		"model": "assessment.organisation",
		"pk": 57
	},
	{
		"fields": {
			"name": "Chesterfield Borough Council",
			"domain_name": "chesterfield.gov.uk",
			"organisation_region": 1,
			"organisation_type": 5
		},
		"model": "assessment.organisation",
		"pk": 58
	},
	{
		"fields": {
			"name": "Chichester District Council",
			"domain_name": "chichester.gov.uk",
			"organisation_region": 6,
			"organisation_type": 5
		},
		"model": "assessment.organisation",
		"pk": 59
	},
	{
		"fields": {
			"name": "Chiltern District Council",
			"domain_name": "chiltern.gov.uk",
			"organisation_region": 6,
			"organisation_type": 5
		},
		"model": "assessment.organisation",
		"pk": 60
	},
	{
		"fields": {
			"name": "Chorley Borough Council",
			"domain_name": "chorley.gov.uk",
			"organisation_region": 5,
			"organisation_type": 5
		},
		"model": "assessment.organisation",
		"pk": 61
	},
	{
		"fields": {
			"name": "City of London Council",
			"domain_name": "cityoflondon.gov.uk",
			"organisation_region": 3,
			"organisation_type": 3
		},
		"model": "assessment.organisation",
		"pk": 62
	},
	{
		"fields": {
			"name": "Colchester Borough Council",
			"domain_name": "colchester.gov.uk",
			"organisation_region": 2,
			"organisation_type": 5
		},
		"model": "assessment.organisation",
		"pk": 63
	},
	{
		"fields": {
			"name": "Copeland Borough Council",
			"domain_name": "copeland.gov.uk",
			"organisation_region": 5,
			"organisation_type": 5
		},
		"model": "assessment.organisation",
		"pk": 64
	},
	{
		"fields": {
			"name": "Corby Borough Council",
			"domain_name": "corby.gov.uk",
			"organisation_region": 1,
			"organisation_type": 5
		},
		"model": "assessment.organisation",
		"pk": 65
	},
	{
		"fields": {
			"name": "Cornwall Council",
			"domain_name": "cornwall.gov.uk",
			"organisation_region": 7,
			"organisation_type": 3
		},
		"model": "assessment.organisation",
		"pk": 66
	},
	{
		"fields": {
			"name": "Cotswold District Council",
			"domain_name": "cotswold.gov.uk",
			"organisation_region": 7,
			"organisation_type": 5
		},
		"model": "assessment.organisation",
		"pk": 67
	},
	{
		"fields": {
			"name": "Coventry City Council",
			"domain_name": "coventry.gov.uk",
			"organisation_region": 8,
			"organisation_type": 1
		},
		"model": "assessment.organisation",
		"pk": 68
	},
	{
		"fields": {
			"name": "Craven District Council",
			"domain_name": "cravendc.gov.uk",
			"organisation_region": 9,
			"organisation_type": 5
		},
		"model": "assessment.organisation",
		"pk": 69
	},
	{
		"fields": {
			"name": "Crawley Borough Council",
			"domain_name": "crawley.gov.uk",
			"organisation_region": 6,
			"organisation_type": 5
		},
		"model": "assessment.organisation",
		"pk": 70
	},
	{
		"fields": {
			"name": "Croydon",
			"domain_name": "croydon.gov.uk",
			"organisation_region": 3,
			"organisation_type": 2
		},
		"model": "assessment.organisation",
		"pk": 71
	},
	{
		"fields": {
			"name": "Cumbria County Council",
			"domain_name": "cumbria.gov.uk",
			"organisation_region": 5,
			"organisation_type": 4
		},
		"model": "assessment.organisation",
		"pk": 72
	},
	{
		"fields": {
			"name": "Dacorum Borough Council",
			"domain_name": "dacorum.gov.uk",
			"organisation_region": 2,
			"organisation_type": 5
		},
		"model": "assessment.organisation",
		"pk": 73
	},
	{
		"fields": {
			"name": "Darlington Borough Council",
			"domain_name": "darlington.gov.uk",
			"organisation_region": 4,
			"organisation_type": 3
		},
		"model": "assessment.organisation",
		"pk": 74
	},
	{
		"fields": {
			"name": "Dartford Borough Council",
			"domain_name": "dartford.gov.uk",
			"organisation_region": 6,
			"organisation_type": 5
		},
		"model": "assessment.organisation",
		"pk": 75
	},
	{
		"fields": {
			"name": "Daventry District Council",
			"domain_name": "daventrydc.gov.uk",
			"organisation_region": 1,
			"organisation_type": 5
		},
		"model": "assessment.organisation",
		"pk": 76
	},
	{
		"fields": {
			"name": "Derby City Council",
			"domain_name": "derby.gov.uk",
			"organisation_region": 1,
			"organisation_type": 3
		},
		"model": "assessment.organisation",
		"pk": 77
	},
	{
		"fields": {
			"name": "Derbyshire County Council",
			"domain_name": "derbyshire.gov.uk",
			"organisation_region": 1,
			"organisation_type": 4
		},
		"model": "assessment.organisation",
		"pk": 78
	},
	{
		"fields": {
			"name": "Derbyshire Dales District Council",
			"domain_name": "derbyshiredales.gov.uk",
			"organisation_region": 1,
			"organisation_type": 5
		},
		"model": "assessment.organisation",
		"pk": 79
	},
	{
		"fields": {
			"name": "Devon County Council",
			"domain_name": "devon.gov.uk",
			"organisation_region": 7,
			"organisation_type": 4
		},
		"model": "assessment.organisation",
		"pk": 80
	},
	{
		"fields": {
			"name": "Doncaster Borough Council",
			"domain_name": "doncaster.gov.uk",
			"organisation_region": 9,
			"organisation_type": 1
		},
		"model": "assessment.organisation",
		"pk": 81
	},
	{
		"fields": {
			"name": "Dorset Council",
			"domain_name": "dorsetcouncil.gov.uk",
			"organisation_region": 7,
			"organisation_type": 3
		},
		"model": "assessment.organisation",
		"pk": 82
	},
	{
		"fields": {
			"name": "Dover District Council",
			"domain_name": "dover.gov.uk",
			"organisation_region": 6,
			"organisation_type": 5
		},
		"model": "assessment.organisation",
		"pk": 83
	},
	{
		"fields": {
			"name": "Dudley Borough Council",
			"domain_name": "dudley.gov.uk",
			"organisation_region": 8,
			"organisation_type": 1
		},
		"model": "assessment.organisation",
		"pk": 84
	},
	{
		"fields": {
			"name": "Durham County Council",
			"domain_name": "durham.gov.uk",
			"organisation_region": 4,
			"organisation_type": 3
		},
		"model": "assessment.organisation",
		"pk": 85
	},
	{
		"fields": {
			"name": "Ealing",
			"domain_name": "ealing.gov.uk",
			"organisation_region": 3,
			"organisation_type": 2
		},
		"model": "assessment.organisation",
		"pk": 86
	},
	{
		"fields": {
			"name": "East Cambridgeshire District Council",
			"domain_name": "eastcambs.gov.uk",
			"organisation_region": 2,
			"organisation_type": 5
		},
		"model": "assessment.organisation",
		"pk": 87
	},
	{
		"fields": {
			"name": "East Devon District Council",
			"domain_name": "eastdevon.gov.uk",
			"organisation_region": 7,
			"organisation_type": 5
		},
		"model": "assessment.organisation",
		"pk": 88
	},
	{
		"fields": {
			"name": "East Hampshire District Council",
			"domain_name": "easthants.gov.uk",
			"organisation_region": 6,
			"organisation_type": 5
		},
		"model": "assessment.organisation",
		"pk": 89
	},
	{
		"fields": {
			"name": "East Hertfordshire District Council",
			"domain_name": "eastherts.gov.uk",
			"organisation_region": 2,
			"organisation_type": 5
		},
		"model": "assessment.organisation",
		"pk": 90
	},
	{
		"fields": {
			"name": "East Lindsey District Council",
			"domain_name": "e-lindsey.gov.uk",
			"organisation_region": 1,
			"organisation_type": 5
		},
		"model": "assessment.organisation",
		"pk": 91
	},
	{
		"fields": {
			"name": "East Northamptonshire District Council",
			"domain_name": "east-northamptonshire.gov.uk",
			"organisation_region": 1,
			"organisation_type": 5
		},
		"model": "assessment.organisation",
		"pk": 92
	},
	{
		"fields": {
			"name": "East Riding of Yorkshire Council",
			"domain_name": "eastbourne.gov.uk",
			"organisation_region": 9,
			"organisation_type": 3
		},
		"model": "assessment.organisation",
		"pk": 93
	},
	{
		"fields": {
			"name": "East Staffordshire Borough Council",
			"domain_name": "eastleigh.gov.uk",
			"organisation_region": 8,
			"organisation_type": 5
		},
		"model": "assessment.organisation",
		"pk": 94
	},
	{
		"fields": {
			"name": "East Suffolk  Council",
			"domain_name": "eastriding.gov.uk",
			"organisation_region": 2,
			"organisation_type": 5
		},
		"model": "assessment.organisation",
		"pk": 95
	},
	{
		"fields": {
			"name": "East Sussex County Council",
			"domain_name": "eaststaffsbc.gov.uk",
			"organisation_region": 6,
			"organisation_type": 4
		},
		"model": "assessment.organisation",
		"pk": 96
	},
	{
		"fields": {
			"name": "Eastbourne Borough Council",
			"domain_name": "eastsuffolk.gov.uk",
			"organisation_region": 6,
			"organisation_type": 5
		},
		"model": "assessment.organisation",
		"pk": 97
	},
	{
		"fields": {
			"name": "Eastleigh Borough Council",
			"domain_name": "eastsussex.gov.uk",
			"organisation_region": 6,
			"organisation_type": 5
		},
		"model": "assessment.organisation",
		"pk": 98
	},
	{
		"fields": {
			"name": "Eden District Council",
			"domain_name": "eden.gov.uk",
			"organisation_region": 5,
			"organisation_type": 5
		},
		"model": "assessment.organisation",
		"pk": 99
	},
	{
		"fields": {
			"name": "Elmbridge Borough Council",
			"domain_name": "elmbridge.gov.uk",
			"organisation_region": 6,
			"organisation_type": 5
		},
		"model": "assessment.organisation",
		"pk": 100
	},
	{
		"fields": {
			"name": "Enfield",
			"domain_name": "enfield.gov.uk",
			"organisation_region": 3,
			"organisation_type": 2
		},
		"model": "assessment.organisation",
		"pk": 101
	},
	{
		"fields": {
			"name": "Epping Forest District Council",
			"domain_name": "eppingforestdc.gov.uk",
			"organisation_region": 2,
			"organisation_type": 5
		},
		"model": "assessment.organisation",
		"pk": 102
	},
	{
		"fields": {
			"name": "Epsom & Ewell Borough Council",
			"domain_name": "epsom-ewell.gov.uk",
			"organisation_region": 6,
			"organisation_type": 5
		},
		"model": "assessment.organisation",
		"pk": 103
	},
	{
		"fields": {
			"name": "Erewash Borough Council",
			"domain_name": "erewash.gov.uk",
			"organisation_region": 1,
			"organisation_type": 5
		},
		"model": "assessment.organisation",
		"pk": 104
	},
	{
		"fields": {
			"name": "Essex County Council",
			"domain_name": "essex.gov.uk",
			"organisation_region": 2,
			"organisation_type": 4
		},
		"model": "assessment.organisation",
		"pk": 105
	},
	{
		"fields": {
			"name": "Exeter City Council",
			"domain_name": "exeter.gov.uk",
			"organisation_region": 7,
			"organisation_type": 5
		},
		"model": "assessment.organisation",
		"pk": 106
	},
	{
		"fields": {
			"name": "Fareham Borough Council",
			"domain_name": "fareham.gov.uk",
			"organisation_region": 6,
			"organisation_type": 5
		},
		"model": "assessment.organisation",
		"pk": 107
	},
	{
		"fields": {
			"name": "Fenland District Council",
			"domain_name": "fenland.gov.uk",
			"organisation_region": 2,
			"organisation_type": 5
		},
		"model": "assessment.organisation",
		"pk": 108
	},
	{
		"fields": {
			"name": "Folkestone and Hythe District Council",
			"domain_name": "folkestone-hythe.gov.uk",
			"organisation_region": 6,
			"organisation_type": 5
		},
		"model": "assessment.organisation",
		"pk": 109
	},
	{
		"fields": {
			"name": "Forest of Dean District Council",
			"domain_name": "fdean.gov.uk",
			"organisation_region": 7,
			"organisation_type": 5
		},
		"model": "assessment.organisation",
		"pk": 110
	},
	{
		"fields": {
			"name": "Fylde Borough Council",
			"domain_name": "fylde.gov.uk",
			"organisation_region": 5,
			"organisation_type": 5
		},
		"model": "assessment.organisation",
		"pk": 111
	},
	{
		"fields": {
			"name": "Gateshead Borough Council",
			"domain_name": "gateshead.gov.uk",
			"organisation_region": 4,
			"organisation_type": 1
		},
		"model": "assessment.organisation",
		"pk": 112
	},
	{
		"fields": {
			"name": "Gedling Borough Council",
			"domain_name": "gedling.gov.uk",
			"organisation_region": 1,
			"organisation_type": 5
		},
		"model": "assessment.organisation",
		"pk": 113
	},
	{
		"fields": {
			"name": "Gloucester City Council",
			"domain_name": "gloucester.gov.uk",
			"organisation_region": 7,
			"organisation_type": 5
		},
		"model": "assessment.organisation",
		"pk": 114
	},
	{
		"fields": {
			"name": "Gloucestershire County Council",
			"domain_name": "gloucestershire.gov.uk",
			"organisation_region": 7,
			"organisation_type": 4
		},
		"model": "assessment.organisation",
		"pk": 115
	},
	{
		"fields": {
			"name": "Gosport Borough Council",
			"domain_name": "gosport.gov.uk",
			"organisation_region": 6,
			"organisation_type": 5
		},
		"model": "assessment.organisation",
		"pk": 116
	},
	{
		"fields": {
			"name": "Gravesham Borough Council",
			"domain_name": "gravesham.gov.uk",
			"organisation_region": 6,
			"organisation_type": 5
		},
		"model": "assessment.organisation",
		"pk": 117
	},
	{
		"fields": {
			"name": "Great Yarmouth Borough Council",
			"domain_name": "great-yarmouth.gov.uk",
			"organisation_region": 2,
			"organisation_type": 5
		},
		"model": "assessment.organisation",
		"pk": 118
	},
	{
		"fields": {
			"name": "Greenwich",
			"domain_name": "royalgreenwich.gov.uk",
			"organisation_region": 3,
			"organisation_type": 2
		},
		"model": "assessment.organisation",
		"pk": 119
	},
	{
		"fields": {
			"name": "Guildford Borough Council",
			"domain_name": "guildford.gov.uk",
			"organisation_region": 6,
			"organisation_type": 5
		},
		"model": "assessment.organisation",
		"pk": 120
	},
	{
		"fields": {
			"name": "Hackney",
			"domain_name": "hackney.gov.uk",
			"organisation_region": 3,
			"organisation_type": 2
		},
		"model": "assessment.organisation",
		"pk": 121
	},
	{
		"fields": {
			"name": "Halton Borough Council",
			"domain_name": "halton.gov.uk",
			"organisation_region": 5,
			"organisation_type": 3
		},
		"model": "assessment.organisation",
		"pk": 122
	},
	{
		"fields": {
			"name": "Hambleton District Council",
			"domain_name": "hambleton.gov.uk",
			"organisation_region": 9,
			"organisation_type": 5
		},
		"model": "assessment.organisation",
		"pk": 123
	},
	{
		"fields": {
			"name": "Hammersmith and Fulham",
			"domain_name": "lbhf.gov.uk",
			"organisation_region": 3,
			"organisation_type": 2
		},
		"model": "assessment.organisation",
		"pk": 124
	},
	{
		"fields": {
			"name": "Hampshire County Council",
			"domain_name": "hants.gov.uk",
			"organisation_region": 6,
			"organisation_type": 4
		},
		"model": "assessment.organisation",
		"pk": 125
	},
	{
		"fields": {
			"name": "Harborough District Council",
			"domain_name": "harborough.gov.uk",
			"organisation_region": 1,
			"organisation_type": 5
		},
		"model": "assessment.organisation",
		"pk": 126
	},
	{
		"fields": {
			"name": "Haringey",
			"domain_name": "haringey.gov.uk",
			"organisation_region": 3,
			"organisation_type": 2
		},
		"model": "assessment.organisation",
		"pk": 127
	},
	{
		"fields": {
			"name": "Harlow District Council",
			"domain_name": "harlow.gov.uk",
			"organisation_region": 2,
			"organisation_type": 5
		},
		"model": "assessment.organisation",
		"pk": 128
	},
	{
		"fields": {
			"name": "Harrogate Borough Council",
			"domain_name": "harrogate.gov.uk",
			"organisation_region": 9,
			"organisation_type": 5
		},
		"model": "assessment.organisation",
		"pk": 129
	},
	{
		"fields": {
			"name": "Harrow",
			"domain_name": "harrow.gov.uk",
			"organisation_region": 3,
			"organisation_type": 2
		},
		"model": "assessment.organisation",
		"pk": 130
	},
	{
		"fields": {
			"name": "Hart District Council",
			"domain_name": "hart.gov.uk",
			"organisation_region": 6,
			"organisation_type": 5
		},
		"model": "assessment.organisation",
		"pk": 131
	},
	{
		"fields": {
			"name": "Hartlepool Borough Council",
			"domain_name": "hartlepool.gov.uk",
			"organisation_region": 4,
			"organisation_type": 3
		},
		"model": "assessment.organisation",
		"pk": 132
	},
	{
		"fields": {
			"name": "Hastings Borough Council",
			"domain_name": "hastings.gov.uk",
			"organisation_region": 6,
			"organisation_type": 5
		},
		"model": "assessment.organisation",
		"pk": 133
	},
	{
		"fields": {
			"name": "Havant Borough Council",
			"domain_name": "havant.gov.uk",
			"organisation_region": 6,
			"organisation_type": 5
		},
		"model": "assessment.organisation",
		"pk": 134
	},
	{
		"fields": {
			"name": "Havering",
			"domain_name": "havering.gov.uk",
			"organisation_region": 3,
			"organisation_type": 2
		},
		"model": "assessment.organisation",
		"pk": 135
	},
	{
		"fields": {
			"name": "Herefordshire Council",
			"domain_name": "herefordshire.gov.uk",
			"organisation_region": 8,
			"organisation_type": 3
		},
		"model": "assessment.organisation",
		"pk": 136
	},
	{
		"fields": {
			"name": "Hertfordshire County Council",
			"domain_name": "hertfordshire.gov.uk",
			"organisation_region": 2,
			"organisation_type": 4
		},
		"model": "assessment.organisation",
		"pk": 137
	},
	{
		"fields": {
			"name": "Hertsmere Borough Council",
			"domain_name": "hertsmere.gov.uk",
			"organisation_region": 2,
			"organisation_type": 5
		},
		"model": "assessment.organisation",
		"pk": 138
	},
	{
		"fields": {
			"name": "High Peak Borough Council",
			"domain_name": "highpeak.gov.uk",
			"organisation_region": 1,
			"organisation_type": 5
		},
		"model": "assessment.organisation",
		"pk": 139
	},
	{
		"fields": {
			"name": "Hillingdon",
			"domain_name": "hillingdon.gov.uk",
			"organisation_region": 3,
			"organisation_type": 2
		},
		"model": "assessment.organisation",
		"pk": 140
	},
	{
		"fields": {
			"name": "Hinckley and Bosworth Borough\nCouncil",
			"domain_name": "hinckley-bosworth.gov.uk",
			"organisation_region": 1,
			"organisation_type": 5
		},
		"model": "assessment.organisation",
		"pk": 141
	},
	{
		"fields": {
			"name": "Horsham District Council",
			"domain_name": "horsham.gov.uk",
			"organisation_region": 6,
			"organisation_type": 5
		},
		"model": "assessment.organisation",
		"pk": 142
	},
	{
		"fields": {
			"name": "Hounslow",
			"domain_name": "hounslow.gov.uk",
			"organisation_region": 3,
			"organisation_type": 2
		},
		"model": "assessment.organisation",
		"pk": 143
	},
	{
		"fields": {
			"name": "Hull City Council",
			"domain_name": "hullcc.gov.uk",
			"organisation_region": 9,
			"organisation_type": 3
		},
		"model": "assessment.organisation",
		"pk": 144
	},
	{
		"fields": {
			"name": "Huntingdonshire District Council",
			"domain_name": "huntingdonshire.gov.uk",
			"organisation_region": 2,
			"organisation_type": 5
		},
		"model": "assessment.organisation",
		"pk": 145
	},
	{
		"fields": {
			"name": "Hyndburn Borough Council",
			"domain_name": "hyndburnbc.gov.uk",
			"organisation_region": 5,
			"organisation_type": 5
		},
		"model": "assessment.organisation",
		"pk": 146
	},
	{
		"fields": {
			"name": "Ipswich Borough Council",
			"domain_name": "ipswich.gov.uk",
			"organisation_region": 2,
			"organisation_type": 5
		},
		"model": "assessment.organisation",
		"pk": 147
	},
	{
		"fields": {
			"name": "Isle of Wight Council",
			"domain_name": "iow.gov.uk",
			"organisation_region": 6,
			"organisation_type": 3
		},
		"model": "assessment.organisation",
		"pk": 148
	},
	{
		"fields": {
			"name": "Isles of Scilly Council",
			"domain_name": "scilly.gov.uk",
			"organisation_region": 7,
			"organisation_type": 3
		},
		"model": "assessment.organisation",
		"pk": 149
	},
	{
		"fields": {
			"name": "Islington",
			"domain_name": "islington.gov.uk",
			"organisation_region": 3,
			"organisation_type": 2
		},
		"model": "assessment.organisation",
		"pk": 150
	},
	{
		"fields": {
			"name": "Kensington and Chelsea",
			"domain_name": "rbkc.gov.uk",
			"organisation_region": 3,
			"organisation_type": 2
		},
		"model": "assessment.organisation",
		"pk": 151
	},
	{
		"fields": {
			"name": "Kent County Council",
			"domain_name": "kent.gov.uk",
			"organisation_region": 6,
			"organisation_type": 4
		},
		"model": "assessment.organisation",
		"pk": 152
	},
	{
		"fields": {
			"name": "Kettering  Borough Council",
			"domain_name": "kettering.gov.uk",
			"organisation_region": 1,
			"organisation_type": 5
		},
		"model": "assessment.organisation",
		"pk": 153
	},
	{
		"fields": {
			"name": "Kings Lynn & West Norfolk Borough Council",
			"domain_name": "west-norfolk.gov.uk",
			"organisation_region": 2,
			"organisation_type": 5
		},
		"model": "assessment.organisation",
		"pk": 154
	},
	{
		"fields": {
			"name": "Kingston upon Thames",
			"domain_name": "kingston.gov.uk",
			"organisation_region": 3,
			"organisation_type": 2
		},
		"model": "assessment.organisation",
		"pk": 155
	},
	{
		"fields": {
			"name": "Kirklees Borough Council",
			"domain_name": "kirklees.gov.uk",
			"organisation_region": 9,
			"organisation_type": 1
		},
		"model": "assessment.organisation",
		"pk": 156
	},
	{
		"fields": {
			"name": "Knowsley Borough Council",
			"domain_name": "knowsley.gov.uk",
			"organisation_region": 5,
			"organisation_type": 1
		},
		"model": "assessment.organisation",
		"pk": 157
	},
	{
		"fields": {
			"name": "Lambeth",
			"domain_name": "lambeth.gov.uk",
			"organisation_region": 3,
			"organisation_type": 2
		},
		"model": "assessment.organisation",
		"pk": 158
	},
	{
		"fields": {
			"name": "Lancashire County Council",
			"domain_name": "lancashire.gov.uk",
			"organisation_region": 5,
			"organisation_type": 4
		},
		"model": "assessment.organisation",
		"pk": 159
	},
	{
		"fields": {
			"name": "Lancaster City Council",
			"domain_name": "lancaster.gov.uk",
			"organisation_region": 5,
			"organisation_type": 5
		},
		"model": "assessment.organisation",
		"pk": 160
	},
	{
		"fields": {
			"name": "Leeds City Council",
			"domain_name": "leeds.gov.uk",
			"organisation_region": 9,
			"organisation_type": 1
		},
		"model": "assessment.organisation",
		"pk": 161
	},
	{
		"fields": {
			"name": "Leicester City Council",
			"domain_name": "leicester.gov.uk",
			"organisation_region": 1,
			"organisation_type": 3
		},
		"model": "assessment.organisation",
		"pk": 162
	},
	{
		"fields": {
			"name": "Leicestershire County Council",
			"domain_name": "leics.gov.uk",
			"organisation_region": 1,
			"organisation_type": 4
		},
		"model": "assessment.organisation",
		"pk": 163
	},
	{
		"fields": {
			"name": "Lewes District Council",
			"domain_name": "lewes.gov.uk",
			"organisation_region": 6,
			"organisation_type": 5
		},
		"model": "assessment.organisation",
		"pk": 164
	},
	{
		"fields": {
			"name": "Lewisham",
			"domain_name": "lewisham.gov.uk",
			"organisation_region": 3,
			"organisation_type": 2
		},
		"model": "assessment.organisation",
		"pk": 165
	},
	{
		"fields": {
			"name": "Lichfield City Council",
			"domain_name": "lichfielddc.gov.uk",
			"organisation_region": 8,
			"organisation_type": 5
		},
		"model": "assessment.organisation",
		"pk": 166
	},
	{
		"fields": {
			"name": "Lincoln City Council",
			"domain_name": "lincoln.gov.uk",
			"organisation_region": 1,
			"organisation_type": 5
		},
		"model": "assessment.organisation",
		"pk": 167
	},
	{
		"fields": {
			"name": "Lincolnshire County Council",
			"domain_name": "lincolnshire.gov.uk",
			"organisation_region": 1,
			"organisation_type": 4
		},
		"model": "assessment.organisation",
		"pk": 168
	},
	{
		"fields": {
			"name": "Liverpool City Council",
			"domain_name": "liverpool.gov.uk",
			"organisation_region": 5,
			"organisation_type": 1
		},
		"model": "assessment.organisation",
		"pk": 169
	},
	{
		"fields": {
			"name": "Luton Borough Council",
			"domain_name": "luton.gov.uk",
			"organisation_region": 2,
			"organisation_type": 3
		},
		"model": "assessment.organisation",
		"pk": 170
	},
	{
		"fields": {
			"name": "Maidstone Borough Council",
			"domain_name": "maidstone.gov.uk",
			"organisation_region": 6,
			"organisation_type": 5
		},
		"model": "assessment.organisation",
		"pk": 171
	},
	{
		"fields": {
			"name": "Maldon District Council",
			"domain_name": "maldon.gov.uk",
			"organisation_region": 2,
			"organisation_type": 5
		},
		"model": "assessment.organisation",
		"pk": 172
	},
	{
		"fields": {
			"name": "Malvern Hills District Council",
			"domain_name": "malvernhills.gov.uk",
			"organisation_region": 8,
			"organisation_type": 5
		},
		"model": "assessment.organisation",
		"pk": 173
	},
	{
		"fields": {
			"name": "Manchester City Council",
			"domain_name": "manchester.gov.uk",
			"organisation_region": 5,
			"organisation_type": 1
		},
		"model": "assessment.organisation",
		"pk": 174
	},
	{
		"fields": {
			"name": "Mansfield District Council",
			"domain_name": "mansfield.gov.uk",
			"organisation_region": 1,
			"organisation_type": 5
		},
		"model": "assessment.organisation",
		"pk": 175
	},
	{
		"fields": {
			"name": "Medway Council",
			"domain_name": "medway.gov.uk",
			"organisation_region": 6,
			"organisation_type": 3
		},
		"model": "assessment.organisation",
		"pk": 176
	},
	{
		"fields": {
			"name": "Melton Borough Council",
			"domain_name": "melton.gov.uk",
			"organisation_region": 1,
			"organisation_type": 5
		},
		"model": "assessment.organisation",
		"pk": 177
	},
	{
		"fields": {
			"name": "Mendip District Council",
			"domain_name": "mendip.gov.uk",
			"organisation_region": 7,
			"organisation_type": 5
		},
		"model": "assessment.organisation",
		"pk": 178
	},
	{
		"fields": {
			"name": "Merton",
			"domain_name": "merton.gov.uk",
			"organisation_region": 3,
			"organisation_type": 2
		},
		"model": "assessment.organisation",
		"pk": 179
	},
	{
		"fields": {
			"name": "Mid Devon District Council",
			"domain_name": "middevon.gov.uk",
			"organisation_region": 7,
			"organisation_type": 5
		},
		"model": "assessment.organisation",
		"pk": 180
	},
	{
		"fields": {
			"name": "Mid Suffolk District Council",
			"domain_name": "midsuffolk.gov.uk",
			"organisation_region": 2,
			"organisation_type": 5
		},
		"model": "assessment.organisation",
		"pk": 181
	},
	{
		"fields": {
			"name": "Mid Sussex District Council",
			"domain_name": "midsussex.gov.uk",
			"organisation_region": 6,
			"organisation_type": 5
		},
		"model": "assessment.organisation",
		"pk": 182
	},
	{
		"fields": {
			"name": "Middlesbrough Borough Council",
			"domain_name": "middlesbrough.gov.uk",
			"organisation_region": 4,
			"organisation_type": 3
		},
		"model": "assessment.organisation",
		"pk": 183
	},
	{
		"fields": {
			"name": "Milton Keynes Council",
			"domain_name": "milton-keynes.gov.uk",
			"organisation_region": 6,
			"organisation_type": 3
		},
		"model": "assessment.organisation",
		"pk": 184
	},
	{
		"fields": {
			"name": "Mole Valley District Council",
			"domain_name": "molevalley.gov.uk",
			"organisation_region": 6,
			"organisation_type": 5
		},
		"model": "assessment.organisation",
		"pk": 185
	},
	{
		"fields": {
			"name": "New Forest District Council",
			"domain_name": "newforestdc.gov.uk",
			"organisation_region": 6,
			"organisation_type": 5
		},
		"model": "assessment.organisation",
		"pk": 186
	},
	{
		"fields": {
			"name": "Newark & Sherwood District Council",
			"domain_name": "newark-sherwooddc.gov.uk",
			"organisation_region": 1,
			"organisation_type": 5
		},
		"model": "assessment.organisation",
		"pk": 187
	},
	{
		"fields": {
			"name": "Newcastle Upon Tyne City Council",
			"domain_name": "newcastle.gov.uk",
			"organisation_region": 4,
			"organisation_type": 1
		},
		"model": "assessment.organisation",
		"pk": 188
	},
	{
		"fields": {
			"name": "Newcastle-Under-Lyme Borough Council",
			"domain_name": "newcastle-staffs.gov.uk",
			"organisation_region": 8,
			"organisation_type": 5
		},
		"model": "assessment.organisation",
		"pk": 189
	},
	{
		"fields": {
			"name": "Newham",
			"domain_name": "newham.gov.uk",
			"organisation_region": 3,
			"organisation_type": 2
		},
		"model": "assessment.organisation",
		"pk": 190
	},
	{
		"fields": {
			"name": "Norfolk County Council",
			"domain_name": "norfolk.gov.uk",
			"organisation_region": 2,
			"organisation_type": 4
		},
		"model": "assessment.organisation",
		"pk": 191
	},
	{
		"fields": {
			"name": "North Devon District Council",
			"domain_name": "northdevon.gov.uk",
			"organisation_region": 7,
			"organisation_type": 5
		},
		"model": "assessment.organisation",
		"pk": 192
	},
	{
		"fields": {
			"name": "North East Derbyshire District Council",
			"domain_name": "ne-derbyshire.gov.uk",
			"organisation_region": 1,
			"organisation_type": 5
		},
		"model": "assessment.organisation",
		"pk": 193
	},
	{
		"fields": {
			"name": "North East Lincolnshire Council",
			"domain_name": "nelincs.gov.uk",
			"organisation_region": 9,
			"organisation_type": 3
		},
		"model": "assessment.organisation",
		"pk": 194
	},
	{
		"fields": {
			"name": "North Hertfordshire District Council",
			"domain_name": "north-herts.gov.uk",
			"organisation_region": 2,
			"organisation_type": 5
		},
		"model": "assessment.organisation",
		"pk": 195
	},
	{
		"fields": {
			"name": "North Kesteven District Council",
			"domain_name": "n-kesteven.gov.uk",
			"organisation_region": 1,
			"organisation_type": 5
		},
		"model": "assessment.organisation",
		"pk": 196
	},
	{
		"fields": {
			"name": "North Lincolnshire Council",
			"domain_name": "northlincs.gov.uk",
			"organisation_region": 9,
			"organisation_type": 3
		},
		"model": "assessment.organisation",
		"pk": 197
	},
	{
		"fields": {
			"name": "North Norfolk District Council",
			"domain_name": "north-norfolk.gov.uk",
			"organisation_region": 2,
			"organisation_type": 5
		},
		"model": "assessment.organisation",
		"pk": 198
	},
	{
		"fields": {
			"name": "North Somerset Council",
			"domain_name": "n-somerset.gov.uk",
			"organisation_region": 7,
			"organisation_type": 3
		},
		"model": "assessment.organisation",
		"pk": 199
	},
	{
		"fields": {
			"name": "North Tyneside Borough Council",
			"domain_name": "northtyneside.gov.uk",
			"organisation_region": 4,
			"organisation_type": 1
		},
		"model": "assessment.organisation",
		"pk": 200
	},
	{
		"fields": {
			"name": "North Warwickshire Borough Council",
			"domain_name": "northwarks.gov.uk",
			"organisation_region": 8,
			"organisation_type": 5
		},
		"model": "assessment.organisation",
		"pk": 201
	},
	{
		"fields": {
			"name": "North West Leicestershire District Council",
			"domain_name": "nwleics.gov.uk",
			"organisation_region": 1,
			"organisation_type": 5
		},
		"model": "assessment.organisation",
		"pk": 202
	},
	{
		"fields": {
			"name": "North Yorkshire County Council",
			"domain_name": "northyorks.gov.uk",
			"organisation_region": 9,
			"organisation_type": 4
		},
		"model": "assessment.organisation",
		"pk": 203
	},
	{
		"fields": {
			"name": "Northampton Borough Council",
			"domain_name": "northampton.gov.uk",
			"organisation_region": 1,
			"organisation_type": 5
		},
		"model": "assessment.organisation",
		"pk": 204
	},
	{
		"fields": {
			"name": "Northamptonshire County Council",
			"domain_name": "northamptonshire.gov.uk",
			"organisation_region": 1,
			"organisation_type": 4
		},
		"model": "assessment.organisation",
		"pk": 205
	},
	{
		"fields": {
			"name": "Northumberland County Council",
			"domain_name": "northumberland.gov.uk",
			"organisation_region": 4,
			"organisation_type": 3
		},
		"model": "assessment.organisation",
		"pk": 206
	},
	{
		"fields": {
			"name": "Norwich City Council",
			"domain_name": "norwich.gov.uk",
			"organisation_region": 2,
			"organisation_type": 5
		},
		"model": "assessment.organisation",
		"pk": 207
	},
	{
		"fields": {
			"name": "Nottingham City Council",
			"domain_name": "nottinghamcity.gov.uk",
			"organisation_region": 1,
			"organisation_type": 3
		},
		"model": "assessment.organisation",
		"pk": 208
	},
	{
		"fields": {
			"name": "Nottinghamshire County Council",
			"domain_name": "nottinghamshire.gov.uk",
			"organisation_region": 1,
			"organisation_type": 4
		},
		"model": "assessment.organisation",
		"pk": 209
	},
	{
		"fields": {
			"name": "Nuneaton & Bedworth Borough Council",
			"domain_name": "nuneatonandbedworth.gov.uk",
			"organisation_region": 8,
			"organisation_type": 5
		},
		"model": "assessment.organisation",
		"pk": 210
	},
	{
		"fields": {
			"name": "Oadby & Wigston Borough Council",
			"domain_name": "oadby-wigston.gov.uk",
			"organisation_region": 1,
			"organisation_type": 5
		},
		"model": "assessment.organisation",
		"pk": 211
	},
	{
		"fields": {
			"name": "Oldham Borough Council",
			"domain_name": "oldham.gov.uk",
			"organisation_region": 5,
			"organisation_type": 1
		},
		"model": "assessment.organisation",
		"pk": 212
	},
	{
		"fields": {
			"name": "Oxford City Council",
			"domain_name": "oxford.gov.uk",
			"organisation_region": 6,
			"organisation_type": 5
		},
		"model": "assessment.organisation",
		"pk": 213
	},
	{
		"fields": {
			"name": "Oxfordshire County Council",
			"domain_name": "oxfordshire.gov.uk",
			"organisation_region": 6,
			"organisation_type": 4
		},
		"model": "assessment.organisation",
		"pk": 214
	},
	{
		"fields": {
			"name": "Pendle Borough Council",
			"domain_name": "pendle.gov.uk",
			"organisation_region": 5,
			"organisation_type": 5
		},
		"model": "assessment.organisation",
		"pk": 215
	},
	{
		"fields": {
			"name": "Peterborough City Council",
			"domain_name": "peterborough.gov.uk",
			"organisation_region": 2,
			"organisation_type": 3
		},
		"model": "assessment.organisation",
		"pk": 216
	},
	{
		"fields": {
			"name": "Plymouth City Council",
			"domain_name": "plymouth.gov.uk",
			"organisation_region": 7,
			"organisation_type": 3
		},
		"model": "assessment.organisation",
		"pk": 217
	},
	{
		"fields": {
			"name": "Portsmouth City Council",
			"domain_name": "portsmouth.gov.uk",
			"organisation_region": 6,
			"organisation_type": 3
		},
		"model": "assessment.organisation",
		"pk": 218
	},
	{
		"fields": {
			"name": "Preston City Council",
			"domain_name": "preston.gov.uk",
			"organisation_region": 5,
			"organisation_type": 5
		},
		"model": "assessment.organisation",
		"pk": 219
	},
	{
		"fields": {
			"name": "Reading Borough Council",
			"domain_name": "reading.gov.uk",
			"organisation_region": 6,
			"organisation_type": 3
		},
		"model": "assessment.organisation",
		"pk": 220
	},
	{
		"fields": {
			"name": "Redbridge",
			"domain_name": "redbridge.gov.uk",
			"organisation_region": 3,
			"organisation_type": 2
		},
		"model": "assessment.organisation",
		"pk": 221
	},
	{
		"fields": {
			"name": "Redcar and Cleveland Borough Council",
			"domain_name": "redcar-cleveland.gov.uk",
			"organisation_region": 4,
			"organisation_type": 3
		},
		"model": "assessment.organisation",
		"pk": 222
	},
	{
		"fields": {
			"name": "Redditch Borough Council",
			"domain_name": "redditchbc.gov.uk",
			"organisation_region": 8,
			"organisation_type": 5
		},
		"model": "assessment.organisation",
		"pk": 223
	},
	{
		"fields": {
			"name": "Reigate & Banstead Borough Council",
			"domain_name": "reigate-banstead.gov.uk",
			"organisation_region": 6,
			"organisation_type": 5
		},
		"model": "assessment.organisation",
		"pk": 224
	},
	{
		"fields": {
			"name": "Ribble Valley Borough Council",
			"domain_name": "ribblevalley.gov.uk",
			"organisation_region": 5,
			"organisation_type": 5
		},
		"model": "assessment.organisation",
		"pk": 225
	},
	{
		"fields": {
			"name": "Richmond upon Thames",
			"domain_name": "richmond.gov.uk",
			"organisation_region": 3,
			"organisation_type": 2
		},
		"model": "assessment.organisation",
		"pk": 226
	},
	{
		"fields": {
			"name": "Richmondshire District Council",
			"domain_name": "richmondshire.gov.uk",
			"organisation_region": 9,
			"organisation_type": 5
		},
		"model": "assessment.organisation",
		"pk": 227
	},
	{
		"fields": {
			"name": "Rochdale Borough Council",
			"domain_name": "rochdale.gov.uk",
			"organisation_region": 5,
			"organisation_type": 1
		},
		"model": "assessment.organisation",
		"pk": 228
	},
	{
		"fields": {
			"name": "Rochford District Council",
			"domain_name": "rochford.gov.uk",
			"organisation_region": 2,
			"organisation_type": 5
		},
		"model": "assessment.organisation",
		"pk": 229
	},
	{
		"fields": {
			"name": "Rossendale Borough Council",
			"domain_name": "rossendale.gov.uk",
			"organisation_region": 5,
			"organisation_type": 5
		},
		"model": "assessment.organisation",
		"pk": 230
	},
	{
		"fields": {
			"name": "Rother District Council",
			"domain_name": "rother.gov.uk",
			"organisation_region": 6,
			"organisation_type": 5
		},
		"model": "assessment.organisation",
		"pk": 231
	},
	{
		"fields": {
			"name": "Rotherham Borough Council",
			"domain_name": "rotherham.gov.uk",
			"organisation_region": 9,
			"organisation_type": 1
		},
		"model": "assessment.organisation",
		"pk": 232
	},
	{
		"fields": {
			"name": "Rugby Borough Council",
			"domain_name": "rugby.gov.uk",
			"organisation_region": 8,
			"organisation_type": 5
		},
		"model": "assessment.organisation",
		"pk": 233
	},
	{
		"fields": {
			"name": "Runnymede Borough Council",
			"domain_name": "runnymede.gov.uk",
			"organisation_region": 6,
			"organisation_type": 5
		},
		"model": "assessment.organisation",
		"pk": 234
	},
	{
		"fields": {
			"name": "Rushcliffe Borough Council",
			"domain_name": "rushcliffe.gov.uk",
			"organisation_region": 1,
			"organisation_type": 5
		},
		"model": "assessment.organisation",
		"pk": 235
	},
	{
		"fields": {
			"name": "Rushmoor Borough Council",
			"domain_name": "rushmoor.gov.uk",
			"organisation_region": 6,
			"organisation_type": 5
		},
		"model": "assessment.organisation",
		"pk": 236
	},
	{
		"fields": {
			"name": "Rutland County Council",
			"domain_name": "rutland.gov.uk",
			"organisation_region": 1,
			"organisation_type": 3
		},
		"model": "assessment.organisation",
		"pk": 237
	},
	{
		"fields": {
			"name": "Ryedale District Council",
			"domain_name": "ryedale.gov.uk",
			"organisation_region": 9,
			"organisation_type": 5
		},
		"model": "assessment.organisation",
		"pk": 238
	},
	{
		"fields": {
			"name": "Salford City Council",
			"domain_name": "salford.gov.uk",
			"organisation_region": 5,
			"organisation_type": 1
		},
		"model": "assessment.organisation",
		"pk": 239
	},
	{
		"fields": {
			"name": "Sandwell Borough Council",
			"domain_name": "sandwell.gov.uk",
			"organisation_region": 8,
			"organisation_type": 1
		},
		"model": "assessment.organisation",
		"pk": 240
	},
	{
		"fields": {
			"name": "Scarborough Borough Council",
			"domain_name": "scarborough.gov.uk",
			"organisation_region": 9,
			"organisation_type": 5
		},
		"model": "assessment.organisation",
		"pk": 241
	},
	{
		"fields": {
			"name": "Sedgemoor District Council",
			"domain_name": "sedgemoor.gov.uk",
			"organisation_region": 7,
			"organisation_type": 5
		},
		"model": "assessment.organisation",
		"pk": 242
	},
	{
		"fields": {
			"name": "Sefton Borough Council",
			"domain_name": "sefton.gov.uk",
			"organisation_region": 5,
			"organisation_type": 1
		},
		"model": "assessment.organisation",
		"pk": 243
	},
	{
		"fields": {
			"name": "Selby District Council",
			"domain_name": "selby.gov.uk",
			"organisation_region": 9,
			"organisation_type": 5
		},
		"model": "assessment.organisation",
		"pk": 244
	},
	{
		"fields": {
			"name": "Sevenoaks District Council",
			"domain_name": "sevenoaks.gov.uk",
			"organisation_region": 6,
			"organisation_type": 5
		},
		"model": "assessment.organisation",
		"pk": 245
	},
	{
		"fields": {
			"name": "Sheffield City Council",
			"domain_name": "sheffield.gov.uk",
			"organisation_region": 9,
			"organisation_type": 1
		},
		"model": "assessment.organisation",
		"pk": 246
	},
	{
		"fields": {
			"name": "Shropshire Council",
			"domain_name": "shropshire.gov.uk",
			"organisation_region": 8,
			"organisation_type": 3
		},
		"model": "assessment.organisation",
		"pk": 247
	},
	{
		"fields": {
			"name": "Slough Borough Council",
			"domain_name": "slough.gov.uk",
			"organisation_region": 6,
			"organisation_type": 3
		},
		"model": "assessment.organisation",
		"pk": 248
	},
	{
		"fields": {
			"name": "Solihull Borough Council",
			"domain_name": "solihull.gov.uk",
			"organisation_region": 8,
			"organisation_type": 1
		},
		"model": "assessment.organisation",
		"pk": 249
	},
	{
		"fields": {
			"name": "Somerset County Council",
			"domain_name": "somerset.gov.uk",
			"organisation_region": 7,
			"organisation_type": 4
		},
		"model": "assessment.organisation",
		"pk": 250
	},
	{
		"fields": {
			"name": "Somerset West and Taunton Council",
			"domain_name": "somersetwestandtaunton.gov.uk",
			"organisation_region": 7,
			"organisation_type": 5
		},
		"model": "assessment.organisation",
		"pk": 251
	},
	{
		"fields": {
			"name": "South Buckinghamshire District\nCouncil",
			"domain_name": "southbucks.gov.uk",
			"organisation_region": 6,
			"organisation_type": 5
		},
		"model": "assessment.organisation",
		"pk": 252
	},
	{
		"fields": {
			"name": "South Cambridgeshire District Council",
			"domain_name": "scambs.gov.uk",
			"organisation_region": 2,
			"organisation_type": 5
		},
		"model": "assessment.organisation",
		"pk": 253
	},
	{
		"fields": {
			"name": "South Derbyshire District Council",
			"domain_name": "south-derbys.gov.uk",
			"organisation_region": 1,
			"organisation_type": 5
		},
		"model": "assessment.organisation",
		"pk": 254
	},
	{
		"fields": {
			"name": "South Gloucestershire Council",
			"domain_name": "southglos.gov.uk",
			"organisation_region": 7,
			"organisation_type": 3
		},
		"model": "assessment.organisation",
		"pk": 255
	},
	{
		"fields": {
			"name": "South Hams District Council",
			"domain_name": "southhams.gov.uk",
			"organisation_region": 7,
			"organisation_type": 5
		},
		"model": "assessment.organisation",
		"pk": 256
	},
	{
		"fields": {
			"name": "South Holland District Council",
			"domain_name": "sholland.gov.uk",
			"organisation_region": 1,
			"organisation_type": 5
		},
		"model": "assessment.organisation",
		"pk": 257
	},
	{
		"fields": {
			"name": "South Kesteven District Council",
			"domain_name": "southkesteven.gov.uk",
			"organisation_region": 1,
			"organisation_type": 5
		},
		"model": "assessment.organisation",
		"pk": 258
	},
	{
		"fields": {
			"name": "South Lakeland District Council",
			"domain_name": "southlakeland.gov.uk",
			"organisation_region": 5,
			"organisation_type": 5
		},
		"model": "assessment.organisation",
		"pk": 259
	},
	{
		"fields": {
			"name": "South Norfolk District Council",
			"domain_name": "south-norfolk.gov.uk",
			"organisation_region": 2,
			"organisation_type": 5
		},
		"model": "assessment.organisation",
		"pk": 260
	},
	{
		"fields": {
			"name": "South Northamptonshire District Council",
			"domain_name": "southnorthants.gov.uk",
			"organisation_region": 1,
			"organisation_type": 5
		},
		"model": "assessment.organisation",
		"pk": 261
	},
	{
		"fields": {
			"name": "South Oxfordshire District Council",
			"domain_name": "southoxon.gov.uk",
			"organisation_region": 6,
			"organisation_type": 5
		},
		"model": "assessment.organisation",
		"pk": 262
	},
	{
		"fields": {
			"name": "South Ribble Borough Council",
			"domain_name": "southribble.gov.uk",
			"organisation_region": 5,
			"organisation_type": 5
		},
		"model": "assessment.organisation",
		"pk": 263
	},
	{
		"fields": {
			"name": "South Somerset District Council",
			"domain_name": "southsomerset.gov.uk",
			"organisation_region": 7,
			"organisation_type": 5
		},
		"model": "assessment.organisation",
		"pk": 264
	},
	{
		"fields": {
			"name": "South Staffordshire District Council",
			"domain_name": "sstaffs.gov.uk",
			"organisation_region": 8,
			"organisation_type": 5
		},
		"model": "assessment.organisation",
		"pk": 265
	},
	{
		"fields": {
			"name": "South Tyneside Borough Council",
			"domain_name": "southtyneside.gov.uk",
			"organisation_region": 4,
			"organisation_type": 1
		},
		"model": "assessment.organisation",
		"pk": 266
	},
	{
		"fields": {
			"name": "Southampton City Council",
			"domain_name": "southampton.gov.uk",
			"organisation_region": 6,
			"organisation_type": 3
		},
		"model": "assessment.organisation",
		"pk": 267
	},
	{
		"fields": {
			"name": "Southend-on-Sea Borough Council",
			"domain_name": "southend.gov.uk",
			"organisation_region": 2,
			"organisation_type": 3
		},
		"model": "assessment.organisation",
		"pk": 268
	},
	{
		"fields": {
			"name": "Southwark",
			"domain_name": "southwark.gov.uk",
			"organisation_region": 3,
			"organisation_type": 2
		},
		"model": "assessment.organisation",
		"pk": 269
	},
	{
		"fields": {
			"name": "Spelthorne Borough Council",
			"domain_name": "spelthorne.gov.uk",
			"organisation_region": 6,
			"organisation_type": 5
		},
		"model": "assessment.organisation",
		"pk": 270
	},
	{
		"fields": {
			"name": "St Albans City Council",
			"domain_name": "stalbans.gov.uk",
			"organisation_region": 2,
			"organisation_type": 5
		},
		"model": "assessment.organisation",
		"pk": 271
	},
	{
		"fields": {
			"name": "St Helens Borough Council",
			"domain_name": "sthelens.gov.uk",
			"organisation_region": 5,
			"organisation_type": 1
		},
		"model": "assessment.organisation",
		"pk": 272
	},
	{
		"fields": {
			"name": "Stafford Borough Council",
			"domain_name": "staffordbc.gov.uk",
			"organisation_region": 8,
			"organisation_type": 5
		},
		"model": "assessment.organisation",
		"pk": 273
	},
	{
		"fields": {
			"name": "Staffordshire County Council",
			"domain_name": "staffordshire.gov.uk",
			"organisation_region": 8,
			"organisation_type": 4
		},
		"model": "assessment.organisation",
		"pk": 274
	},
	{
		"fields": {
			"name": "Staffordshire Moorlands District\nCouncil",
			"domain_name": "staffsmoorlands.gov.uk",
			"organisation_region": 8,
			"organisation_type": 5
		},
		"model": "assessment.organisation",
		"pk": 275
	},
	{
		"fields": {
			"name": "Stevenage Borough Council",
			"domain_name": "stevenage.gov.uk",
			"organisation_region": 2,
			"organisation_type": 5
		},
		"model": "assessment.organisation",
		"pk": 276
	},
	{
		"fields": {
			"name": "Stockport Borough Council",
			"domain_name": "stockport.gov.uk",
			"organisation_region": 5,
			"organisation_type": 1
		},
		"model": "assessment.organisation",
		"pk": 277
	},
	{
		"fields": {
			"name": "Stockton-on-Tees Borough Council",
			"domain_name": "stockton.gov.uk",
			"organisation_region": 4,
			"organisation_type": 3
		},
		"model": "assessment.organisation",
		"pk": 278
	},
	{
		"fields": {
			"name": "Stoke-on-Trent City Council",
			"domain_name": "stoke.gov.uk",
			"organisation_region": 8,
			"organisation_type": 3
		},
		"model": "assessment.organisation",
		"pk": 279
	},
	{
		"fields": {
			"name": "Stratford on Avon District Council",
			"domain_name": "stratford.gov.uk",
			"organisation_region": 8,
			"organisation_type": 5
		},
		"model": "assessment.organisation",
		"pk": 280
	},
	{
		"fields": {
			"name": "Stroud District Council",
			"domain_name": "stroud.gov.uk",
			"organisation_region": 7,
			"organisation_type": 5
		},
		"model": "assessment.organisation",
		"pk": 281
	},
	{
		"fields": {
			"name": "Suffolk County Council",
			"domain_name": "suffolk.gov.uk",
			"organisation_region": 2,
			"organisation_type": 4
		},
		"model": "assessment.organisation",
		"pk": 282
	},
	{
		"fields": {
			"name": "Sunderland City Council",
			"domain_name": "sunderland.gov.uk",
			"organisation_region": 4,
			"organisation_type": 1
		},
		"model": "assessment.organisation",
		"pk": 283
	},
	{
		"fields": {
			"name": "Surrey County Council",
			"domain_name": "surreycc.gov.uk",
			"organisation_region": 6,
			"organisation_type": 4
		},
		"model": "assessment.organisation",
		"pk": 284
	},
	{
		"fields": {
			"name": "Surrey Heath Borough Council",
			"domain_name": "surreyheath.gov.uk",
			"organisation_region": 6,
			"organisation_type": 5
		},
		"model": "assessment.organisation",
		"pk": 285
	},
	{
		"fields": {
			"name": "Sutton",
			"domain_name": "sutton.gov.uk",
			"organisation_region": 3,
			"organisation_type": 2
		},
		"model": "assessment.organisation",
		"pk": 286
	},
	{
		"fields": {
			"name": "Swale Borough Council",
			"domain_name": "swale.gov.uk",
			"organisation_region": 6,
			"organisation_type": 5
		},
		"model": "assessment.organisation",
		"pk": 287
	},
	{
		"fields": {
			"name": "Swindon Borough Council",
			"domain_name": "swindon.gov.uk",
			"organisation_region": 7,
			"organisation_type": 3
		},
		"model": "assessment.organisation",
		"pk": 288
	},
	{
		"fields": {
			"name": "Tameside Borough Council",
			"domain_name": "tameside.gov.uk",
			"organisation_region": 5,
			"organisation_type": 1
		},
		"model": "assessment.organisation",
		"pk": 289
	},
	{
		"fields": {
			"name": "Tamworth Borough Council",
			"domain_name": "tamworth.gov.uk",
			"organisation_region": 8,
			"organisation_type": 5
		},
		"model": "assessment.organisation",
		"pk": 290
	},
	{
		"fields": {
			"name": "Tandridge District Council",
			"domain_name": "tandridge.gov.uk",
			"organisation_region": 6,
			"organisation_type": 5
		},
		"model": "assessment.organisation",
		"pk": 291
	},
	{
		"fields": {
			"name": "Teignbridge District Council",
			"domain_name": "teignbridge.gov.uk",
			"organisation_region": 7,
			"organisation_type": 5
		},
		"model": "assessment.organisation",
		"pk": 292
	},
	{
		"fields": {
			"name": "Telford and Wrekin Borough Council",
			"domain_name": "telford.gov.uk",
			"organisation_region": 8,
			"organisation_type": 3
		},
		"model": "assessment.organisation",
		"pk": 293
	},
	{
		"fields": {
			"name": "Tendring District Council",
			"domain_name": "tendringdc.gov.uk",
			"organisation_region": 2,
			"organisation_type": 5
		},
		"model": "assessment.organisation",
		"pk": 294
	},
	{
		"fields": {
			"name": "Test Valley Borough Council",
			"domain_name": "testvalley.gov.uk",
			"organisation_region": 6,
			"organisation_type": 5
		},
		"model": "assessment.organisation",
		"pk": 295
	},
	{
		"fields": {
			"name": "Tewkesbury Borough Council",
			"domain_name": "tewkesbury.gov.uk",
			"organisation_region": 7,
			"organisation_type": 5
		},
		"model": "assessment.organisation",
		"pk": 296
	},
	{
		"fields": {
			"name": "Thanet District Council",
			"domain_name": "thanet.gov.uk",
			"organisation_region": 6,
			"organisation_type": 5
		},
		"model": "assessment.organisation",
		"pk": 297
	},
	{
		"fields": {
			"name": "Three Rivers District Council",
			"domain_name": "threerivers.gov.uk",
			"organisation_region": 2,
			"organisation_type": 5
		},
		"model": "assessment.organisation",
		"pk": 298
	},
	{
		"fields": {
			"name": "Thurrock Council",
			"domain_name": "thurrock.gov.uk",
			"organisation_region": 2,
			"organisation_type": 3
		},
		"model": "assessment.organisation",
		"pk": 299
	},
	{
		"fields": {
			"name": "Tonbridge & Malling Borough Council",
			"domain_name": "tmbc.gov.uk",
			"organisation_region": 6,
			"organisation_type": 5
		},
		"model": "assessment.organisation",
		"pk": 300
	},
	{
		"fields": {
			"name": "Torbay Council",
			"domain_name": "torbay.gov.uk",
			"organisation_region": 7,
			"organisation_type": 3
		},
		"model": "assessment.organisation",
		"pk": 301
	},
	{
		"fields": {
			"name": "Torridge District Council",
			"domain_name": "torridge.gov.uk",
			"organisation_region": 7,
			"organisation_type": 5
		},
		"model": "assessment.organisation",
		"pk": 302
	},
	{
		"fields": {
			"name": "Tower Hamlets",
			"domain_name": "towerhamlets.gov.uk",
			"organisation_region": 3,
			"organisation_type": 2
		},
		"model": "assessment.organisation",
		"pk": 303
	},
	{
		"fields": {
			"name": "Trafford Borough Council",
			"domain_name": "trafford.gov.uk",
			"organisation_region": 5,
			"organisation_type": 1
		},
		"model": "assessment.organisation",
		"pk": 304
	},
	{
		"fields": {
			"name": "Tunbridge Wells Borough Council",
			"domain_name": "tunbridgewells.gov.uk",
			"organisation_region": 6,
			"organisation_type": 5
		},
		"model": "assessment.organisation",
		"pk": 305
	},
	{
		"fields": {
			"name": "Uttlesford District Council",
			"domain_name": "uttlesford.gov.uk",
			"organisation_region": 2,
			"organisation_type": 5
		},
		"model": "assessment.organisation",
		"pk": 306
	},
	{
		"fields": {
			"name": "Vale of White Horse District Council",
			"domain_name": "valeofglamorgan.gov.uk",
			"organisation_region": 6,
			"organisation_type": 5
		},
		"model": "assessment.organisation",
		"pk": 307
	},
	{
		"fields": {
			"name": "Wakefield City Council",
			"domain_name": "wakefield.gov.uk",
			"organisation_region": 9,
			"organisation_type": 1
		},
		"model": "assessment.organisation",
		"pk": 308
	},
	{
		"fields": {
			"name": "Walsall Borough Council",
			"domain_name": "walsall.gov.uk",
			"organisation_region": 8,
			"organisation_type": 1
		},
		"model": "assessment.organisation",
		"pk": 309
	},
	{
		"fields": {
			"name": "Waltham Forest",
			"domain_name": "walthamforest.gov.uk",
			"organisation_region": 3,
			"organisation_type": 2
		},
		"model": "assessment.organisation",
		"pk": 310
	},
	{
		"fields": {
			"name": "Wandsworth",
			"domain_name": "wandsworth.gov.uk",
			"organisation_region": 3,
			"organisation_type": 2
		},
		"model": "assessment.organisation",
		"pk": 311
	},
	{
		"fields": {
			"name": "Warrington Borough Council",
			"domain_name": "warrington.gov.uk",
			"organisation_region": 5,
			"organisation_type": 3
		},
		"model": "assessment.organisation",
		"pk": 312
	},
	{
		"fields": {
			"name": "Warwick District Council",
			"domain_name": "warwickdc.gov.uk",
			"organisation_region": 8,
			"organisation_type": 5
		},
		"model": "assessment.organisation",
		"pk": 313
	},
	{
		"fields": {
			"name": "Warwickshire County Council",
			"domain_name": "warwickshire.gov.uk",
			"organisation_region": 8,
			"organisation_type": 4
		},
		"model": "assessment.organisation",
		"pk": 314
	},
	{
		"fields": {
			"name": "Watford Borough Council",
			"domain_name": "watford.gov.uk",
			"organisation_region": 2,
			"organisation_type": 5
		},
		"model": "assessment.organisation",
		"pk": 315
	},
	{
		"fields": {
			"name": "Waverley Borough Council",
			"domain_name": "waverley.gov.uk",
			"organisation_region": 6,
			"organisation_type": 5
		},
		"model": "assessment.organisation",
		"pk": 316
	},
	{
		"fields": {
			"name": "Wealden District Council",
			"domain_name": "wealden.gov.uk",
			"organisation_region": 6,
			"organisation_type": 5
		},
		"model": "assessment.organisation",
		"pk": 317
	},
	{
		"fields": {
			"name": "Wellingborough Borough Council",
			"domain_name": "wellingborough.gov.uk",
			"organisation_region": 1,
			"organisation_type": 5
		},
		"model": "assessment.organisation",
		"pk": 318
	},
	{
		"fields": {
			"name": "Welwyn Hatfield Borough Council",
			"domain_name": "welhat.gov.uk",
			"organisation_region": 2,
			"organisation_type": 5
		},
		"model": "assessment.organisation",
		"pk": 319
	},
	{
		"fields": {
			"name": "West Berkshire Council",
			"domain_name": "westberks.gov.uk",
			"organisation_region": 6,
			"organisation_type": 3
		},
		"model": "assessment.organisation",
		"pk": 320
	},
	{
		"fields": {
			"name": "West Devon District Council",
			"domain_name": "westdevon.gov.uk",
			"organisation_region": 7,
			"organisation_type": 5
		},
		"model": "assessment.organisation",
		"pk": 321
	},
	{
		"fields": {
			"name": "West Lancashire District Council",
			"domain_name": "westlancs.gov.uk",
			"organisation_region": 5,
			"organisation_type": 5
		},
		"model": "assessment.organisation",
		"pk": 322
	},
	{
		"fields": {
			"name": "West Lindsey District Council",
			"domain_name": "westminster.gov.uk",
			"organisation_region": 1,
			"organisation_type": 5
		},
		"model": "assessment.organisation",
		"pk": 323
	},
	{
		"fields": {
			"name": "West Oxfordshire District Council",
			"domain_name": "westoxon.gov.uk",
			"organisation_region": 6,
			"organisation_type": 5
		},
		"model": "assessment.organisation",
		"pk": 324
	},
	{
		"fields": {
			"name": "West Suffolk Council",
			"domain_name": "westsomersetonline.gov.uk",
			"organisation_region": 2,
			"organisation_type": 5
		},
		"model": "assessment.organisation",
		"pk": 325
	},
	{
		"fields": {
			"name": "West Sussex County Council",
			"domain_name": "westsussex.gov.uk",
			"organisation_region": 6,
			"organisation_type": 4
		},
		"model": "assessment.organisation",
		"pk": 326
	},
	{
		"fields": {
			"name": "Westminster",
			"domain_name": "westminster.gov.uk",
			"organisation_region": 3,
			"organisation_type": 2
		},
		"model": "assessment.organisation",
		"pk": 327
	},
	{
		"fields": {
			"name": "Wigan Borough Council",
			"domain_name": "weymouth.gov.uk",
			"organisation_region": 5,
			"organisation_type": 1
		},
		"model": "assessment.organisation",
		"pk": 328
	},
	{
		"fields": {
			"name": "Wiltshire Council",
			"domain_name": "wiltshire.gov.uk",
			"organisation_region": 7,
			"organisation_type": 3
		},
		"model": "assessment.organisation",
		"pk": 329
	},
	{
		"fields": {
			"name": "Winchester City Council",
			"domain_name": "winchester.gov.uk",
			"organisation_region": 6,
			"organisation_type": 5
		},
		"model": "assessment.organisation",
		"pk": 330
	},
	{
		"fields": {
			"name": "Windsor and Maidenhead Borough Council",
			"domain_name": "rbwm.gov.uk",
			"organisation_region": 6,
			"organisation_type": 3
		},
		"model": "assessment.organisation",
		"pk": 331
	},
	{
		"fields": {
			"name": "Wirral Borough Council",
			"domain_name": "wirral.gov.uk",
			"organisation_region": 5,
			"organisation_type": 1
		},
		"model": "assessment.organisation",
		"pk": 332
	},
	{
		"fields": {
			"name": "Woking Borough Council",
			"domain_name": "woking.gov.uk",
			"organisation_region": 6,
			"organisation_type": 5
		},
		"model": "assessment.organisation",
		"pk": 333
	},
	{
		"fields": {
			"name": "Wokingham Borough Council",
			"domain_name": "wokingham.gov.uk",
			"organisation_region": 6,
			"organisation_type": 3
		},
		"model": "assessment.organisation",
		"pk": 334
	},
	{
		"fields": {
			"name": "Wolverhampton City Council",
			"domain_name": "wolverhampton.gov.uk",
			"organisation_region": 8,
			"organisation_type": 1
		},
		"model": "assessment.organisation",
		"pk": 335
	},
	{
		"fields": {
			"name": "Worcester City Council",
			"domain_name": "worcester.gov.uk",
			"organisation_region": 8,
			"organisation_type": 5
		},
		"model": "assessment.organisation",
		"pk": 336
	},
	{
		"fields": {
			"name": "Worcestershire County Council",
			"domain_name": "worcestershire.gov.uk",
			"organisation_region": 8,
			"organisation_type": 4
		},
		"model": "assessment.organisation",
		"pk": 337
	},
	{
		"fields": {
			"name": "Worthing Borough Council",
			"domain_name": "adur-worthing.gov.uk",
			"organisation_region": 6,
			"organisation_type": 5
		},
		"model": "assessment.organisation",
		"pk": 338
	},
	{
		"fields": {
			"name": "Wychavon District Council",
			"domain_name": "wychavon.gov.uk",
			"organisation_region": 8,
			"organisation_type": 5
		},
		"model": "assessment.organisation",
		"pk": 339
	},
	{
		"fields": {
			"name": "Wycombe District Council",
			"domain_name": "wycombe.gov.uk",
			"organisation_region": 6,
			"organisation_type": 5
		},
		"model": "assessment.organisation",
		"pk": 340
	},
	{
		"fields": {
			"name": "Wyre Borough Council",
			"domain_name": "wyre.gov.uk",
			"organisation_region": 5,
			"organisation_type": 5
		},
		"model": "assessment.organisation",
		"pk": 341
	},
	{
		"fields": {
			"name": "Wyre Forest District Council",
			"domain_name": "wyreforestdc.gov.uk",
			"organisation_region": 8,
			"organisation_type": 5
		},
		"model": "assessment.organisation",
		"pk": 342
	},
	{
		"fields": {
			"name": "City of York Council",
			"domain_name": "york.gov.uk",
			"organisation_region": 9,
			"organisation_type": 3
		},
		"model": "assessment.organisation",
		"pk": 343
	}
]